concur/__init__.py
concur/colors.py
concur/core.py
concur/draw.py
concur/testing.py
concur/widgets.py
concur/extra_widgets/__init__.py
concur/extra_widgets/draggable.py
concur/extra_widgets/frame.py
concur/extra_widgets/image.py
concur/extra_widgets/pan_zoom.py
concur/integrations/__init__.py
concur/integrations/glfw.py
concur/integrations/opengl.py
concur/integrations/puppet.py
concur/integrations/quick.py
concur-0.11.0.dist-info/LICENSE
concur-0.11.0.dist-info/METADATA
concur-0.11.0.dist-info/WHEEL
concur-0.11.0.dist-info/top_level.txt
concur-0.11.0.dist-info/RECORD
