Metadata-Version: 2.1
Name: concur
Version: 0.11.0
Summary: Concur UI Framework for Python
Home-page: https://potocpav.github.io/python-concur-docs/homepage.html
Author: Pavel Potocek
Author-email: pavelpotocek@gmail.com
Project-URL: Documentation, https://potocpav.github.io/python-concur-docs/master
Project-URL: Source Code, https://github.com/potocpav/python-concur
Project-URL: Bug Tracker, https://github.com/potocpav/python-concur/issues
Classifier: Programming Language :: Python :: 3
Classifier: Programming Language :: Python :: 3.10
Classifier: Programming Language :: Python :: 3.11
Classifier: Programming Language :: Python :: 3.12
Classifier: License :: OSI Approved :: MIT License
Classifier: Operating System :: OS Independent
Classifier: Intended Audience :: Developers
Classifier: Intended Audience :: Science/Research
Classifier: Topic :: Software Development :: User Interfaces
Classifier: Topic :: Scientific/Engineering :: Visualization
Requires-Python: >=3.6
License-File: LICENSE
Requires-Dist: imgui>=2.0.0
Requires-Dist: Pillow
Requires-Dist: numpy
Requires-Dist: glfw
Requires-Dist: PyOpenGL
Requires-Dist: imageio
Requires-Dist: imageio-ffmpeg
